pydlutils/__init__.py
pydlutils/basic/__init__.py
pydlutils/basic/registry.py
pydlutils/basic/yaml.py
pydlutils/engine/__init__.py
pydlutils/engine/light_det.py
pydlutils/engine/light_trial.py
pydlutils/engine/mlflow_helper.py
pydlutils/peft/__init__.py
pydlutils/peft/registry.py
pydlutils/thirdparty/__init__.py
pydlutils/thirdparty/colmap/__init__.py
pydlutils/thirdparty/colmap/build.py
pydlutils/thirdparty/colmap/build_windows_app.py
pydlutils/thirdparty/colmap/bundler_to_ply.py
pydlutils/thirdparty/colmap/clang_format_code.py
pydlutils/thirdparty/colmap/crawl_camera_specs.py
pydlutils/thirdparty/colmap/database.py
pydlutils/thirdparty/colmap/export_inlier_matches.py
pydlutils/thirdparty/colmap/export_inlier_pairs.py
pydlutils/thirdparty/colmap/export_to_bundler.py
pydlutils/thirdparty/colmap/export_to_visualsfm.py
pydlutils/thirdparty/colmap/flickr_downloader.py
pydlutils/thirdparty/colmap/merge_ply_files.py
pydlutils/thirdparty/colmap/nvm_to_ply.py
pydlutils/thirdparty/colmap/plyfile.py
pydlutils/thirdparty/colmap/read_write_dense.py
pydlutils/thirdparty/colmap/read_write_fused_vis.py
pydlutils/thirdparty/colmap/read_write_model.py
pydlutils/thirdparty/colmap/test_read_write_dense.py
pydlutils/thirdparty/colmap/test_read_write_fused_vis.py
pydlutils/thirdparty/colmap/test_read_write_model.py
pydlutils/thirdparty/colmap/visualize_model.py
pydlutils/torch/__init__.py
pydlutils/torch/registry.py
pydlutils/torch/seed.py
pydlutils/torch/timer.py
pydlutils/transformers/__init__.py
pydlutils/transformers/registry.py
pydlutils-0.0.6.dist-info/LICENSE
pydlutils-0.0.6.dist-info/METADATA
pydlutils-0.0.6.dist-info/WHEEL
pydlutils-0.0.6.dist-info/top_level.txt
pydlutils-0.0.6.dist-info/RECORD
